adventurelib.py
adventurelib-1.2.1.dist-info/LICENSE
adventurelib-1.2.1.dist-info/METADATA
adventurelib-1.2.1.dist-info/WHEEL
adventurelib-1.2.1.dist-info/top_level.txt
adventurelib-1.2.1.dist-info/RECORD
