Metadata-Version: 2.1
Name: adventurelib
Version: 1.2.1
Summary: Easy text adventures
Home-page: https://github.com/lordmauve/adventurelib
Author: Daniel Pope
Author-email: mauve@mauveweb.co.uk
License: UNKNOWN
Project-URL: Documentation, https://adventurelib.readthedocs.io/
Platform: UNKNOWN
Classifier: Development Status :: 5 - Production/Stable
Classifier: Intended Audience :: Education
Classifier: License :: OSI Approved :: MIT License
Classifier: Programming Language :: Python :: 3 :: Only
Classifier: Topic :: Education
Classifier: Topic :: Games/Entertainment
Requires-Python: >=3
Requires-Dist: backports.shutil-get-terminal-size (>=1.0.0) ; python_version < "3.3"
